ppi_py/__init__.py
ppi_py/baselines.py
ppi_py/cross_ppi.py
ppi_py/ppi.py
ppi_py/datasets/__init__.py
ppi_py/datasets/datasets.py
ppi_py/utils/__init__.py
ppi_py/utils/dataset_utils.py
ppi_py/utils/statistics_utils.py
tests/__init__.py
tests/test_cross.py
tests/test_logistic.py
tests/test_mean.py
tests/test_ols.py
tests/test_quantile.py
ppi_python-0.2.2.dist-info/LICENSE
ppi_python-0.2.2.dist-info/METADATA
ppi_python-0.2.2.dist-info/WHEEL
ppi_python-0.2.2.dist-info/top_level.txt
ppi_python-0.2.2.dist-info/RECORD
