Metadata-Version: 2.1
Name: ppi-python
Version: 0.2.2
Summary: Prediction-Powered Inference
License-File: LICENSE
Requires-Dist: numpy
Requires-Dist: numba
Requires-Dist: pandas
Requires-Dist: statsmodels
Requires-Dist: scikit-learn
Requires-Dist: gdown
